odoo/addons/l10n_ro_dvi/README.rst
odoo/addons/l10n_ro_dvi/__init__.py
odoo/addons/l10n_ro_dvi/__manifest__.py
odoo/addons/l10n_ro_dvi/i18n/ro.po
odoo/addons/l10n_ro_dvi/models/__init__.py
odoo/addons/l10n_ro_dvi/models/account_invoice.py
odoo/addons/l10n_ro_dvi/models/stock_landed_cost.py
odoo/addons/l10n_ro_dvi/readme/CONTRIBUTORS.rst
odoo/addons/l10n_ro_dvi/readme/DESCRIPTION.rst
odoo/addons/l10n_ro_dvi/static/description/icon.png
odoo/addons/l10n_ro_dvi/static/description/icon.svg
odoo/addons/l10n_ro_dvi/static/description/index.html
odoo/addons/l10n_ro_dvi/tests/__init__.py
odoo/addons/l10n_ro_dvi/tests/test_dvi.py
odoo/addons/l10n_ro_dvi/views/account_invoice_view.xml
odoo/addons/l10n_ro_dvi/views/stock_landed_cost_view.xml
odoo/addons/l10n_ro_dvi/wizard/__init__.py
odoo/addons/l10n_ro_dvi/wizard/account_dvi.py
odoo/addons/l10n_ro_dvi/wizard/account_dvi_view.xml
odoo13_addon_l10n_ro_dvi-13.0.1.1.0.dist-info/METADATA
odoo13_addon_l10n_ro_dvi-13.0.1.1.0.dist-info/WHEEL
odoo13_addon_l10n_ro_dvi-13.0.1.1.0.dist-info/top_level.txt
odoo13_addon_l10n_ro_dvi-13.0.1.1.0.dist-info/RECORD
